StockDataInterface/StockDataInterface.py
StockDataInterface/__init__.py
stock-data-interface/StockDataInterface.py
stock-data-interface/__init__.py
StcokDataInterface-1.0.9.dist-info/LICENSE
StcokDataInterface-1.0.9.dist-info/METADATA
StcokDataInterface-1.0.9.dist-info/WHEEL
StcokDataInterface-1.0.9.dist-info/top_level.txt
StcokDataInterface-1.0.9.dist-info/RECORD
