Metadata-Version: 2.1
Name: StcokDataInterface
Version: 1.0.9
Summary: An API for Yahoo Finance that collects current and historical stock data
Home-page: https://github.com/nlatham1999/StockAPI
Author: nick latham
Author-email: nlatham@zagmail.gonzaga.edu
License: UNKNOWN
Platform: UNKNOWN
Classifier: Programming Language :: Python :: 3
Classifier: License :: OSI Approved :: MIT License
Classifier: Operating System :: OS Independent
Requires-Python: >=3.6
